{
  "_instructions": "Fill 'result' with '1' (home win), 'X' (draw) or '2' (away win) as matches are played. Set 'champion' when the tournament ends.",
  "champion": null,
  "matches": {
    "A1": {"home": "Mexico",       "away": "South Africa",   "result": null},
    "A2": {"home": "Mexico",       "away": "South Korea",    "result": null},
    "A3": {"home": "Mexico",       "away": "Czech Republic", "result": null},
    "A4": {"home": "South Africa", "away": "South Korea",    "result": null},
    "A5": {"home": "South Africa", "away": "Czech Republic", "result": null},
    "A6": {"home": "South Korea",  "away": "Czech Republic", "result": null},

    "B1": {"home": "Canada",              "away": "Bosnia-Herzegovina", "result": null},
    "B2": {"home": "Canada",              "away": "Qatar",              "result": null},
    "B3": {"home": "Canada",              "away": "Switzerland",        "result": null},
    "B4": {"home": "Bosnia-Herzegovina",  "away": "Qatar",              "result": null},
    "B5": {"home": "Bosnia-Herzegovina",  "away": "Switzerland",        "result": null},
    "B6": {"home": "Qatar",               "away": "Switzerland",        "result": null},

    "C1": {"home": "Brazil",   "away": "Morocco",  "result": null},
    "C2": {"home": "Brazil",   "away": "Haiti",    "result": null},
    "C3": {"home": "Brazil",   "away": "Scotland", "result": null},
    "C4": {"home": "Morocco",  "away": "Haiti",    "result": null},
    "C5": {"home": "Morocco",  "away": "Scotland", "result": null},
    "C6": {"home": "Haiti",    "away": "Scotland", "result": null},

    "D1": {"home": "USA",       "away": "Paraguay",   "result": null},
    "D2": {"home": "USA",       "away": "Australia",  "result": null},
    "D3": {"home": "USA",       "away": "Türkiye",    "result": null},
    "D4": {"home": "Paraguay",  "away": "Australia",  "result": null},
    "D5": {"home": "Paraguay",  "away": "Türkiye",    "result": null},
    "D6": {"home": "Australia", "away": "Türkiye",    "result": null},

    "E1": {"home": "Germany",     "away": "Curaçao",      "result": null},
    "E2": {"home": "Germany",     "away": "Ivory Coast",  "result": null},
    "E3": {"home": "Germany",     "away": "Ecuador",      "result": null},
    "E4": {"home": "Curaçao",     "away": "Ivory Coast",  "result": null},
    "E5": {"home": "Curaçao",     "away": "Ecuador",      "result": null},
    "E6": {"home": "Ivory Coast", "away": "Ecuador",      "result": null},

    "F1": {"home": "Netherlands", "away": "Japan",    "result": null},
    "F2": {"home": "Netherlands", "away": "Sweden",   "result": null},
    "F3": {"home": "Netherlands", "away": "Tunisia",  "result": null},
    "F4": {"home": "Japan",       "away": "Sweden",   "result": null},
    "F5": {"home": "Japan",       "away": "Tunisia",  "result": null},
    "F6": {"home": "Sweden",      "away": "Tunisia",  "result": null},

    "G1": {"home": "Belgium",     "away": "Egypt",       "result": null},
    "G2": {"home": "Belgium",     "away": "Iran",        "result": null},
    "G3": {"home": "Belgium",     "away": "New Zealand", "result": null},
    "G4": {"home": "Egypt",       "away": "Iran",        "result": null},
    "G5": {"home": "Egypt",       "away": "New Zealand", "result": null},
    "G6": {"home": "Iran",        "away": "New Zealand", "result": null},

    "H1": {"home": "Spain",        "away": "Cape Verde",   "result": null},
    "H2": {"home": "Spain",        "away": "Saudi Arabia", "result": null},
    "H3": {"home": "Spain",        "away": "Uruguay",      "result": null},
    "H4": {"home": "Cape Verde",   "away": "Saudi Arabia", "result": null},
    "H5": {"home": "Cape Verde",   "away": "Uruguay",      "result": null},
    "H6": {"home": "Saudi Arabia", "away": "Uruguay",      "result": null},

    "I1": {"home": "France",  "away": "Senegal", "result": null},
    "I2": {"home": "France",  "away": "Iraq",    "result": null},
    "I3": {"home": "France",  "away": "Norway",  "result": null},
    "I4": {"home": "Senegal", "away": "Iraq",    "result": null},
    "I5": {"home": "Senegal", "away": "Norway",  "result": null},
    "I6": {"home": "Iraq",    "away": "Norway",  "result": null},

    "J1": {"home": "Argentina", "away": "Algeria", "result": null},
    "J2": {"home": "Argentina", "away": "Austria", "result": null},
    "J3": {"home": "Argentina", "away": "Jordan",  "result": null},
    "J4": {"home": "Algeria",   "away": "Austria", "result": null},
    "J5": {"home": "Algeria",   "away": "Jordan",  "result": null},
    "J6": {"home": "Austria",   "away": "Jordan",  "result": null},

    "K1": {"home": "Portugal",   "away": "DR Congo",   "result": null},
    "K2": {"home": "Portugal",   "away": "Uzbekistan", "result": null},
    "K3": {"home": "Portugal",   "away": "Colombia",   "result": null},
    "K4": {"home": "DR Congo",   "away": "Uzbekistan", "result": null},
    "K5": {"home": "DR Congo",   "away": "Colombia",   "result": null},
    "K6": {"home": "Uzbekistan", "away": "Colombia",   "result": null},

    "L1": {"home": "England",  "away": "Croatia", "result": null},
    "L2": {"home": "England",  "away": "Ghana",   "result": null},
    "L3": {"home": "England",  "away": "Panama",  "result": null},
    "L4": {"home": "Croatia",  "away": "Ghana",   "result": null},
    "L5": {"home": "Croatia",  "away": "Panama",  "result": null},
    "L6": {"home": "Ghana",    "away": "Panama",  "result": null}
  }
}
